frittomisto/__init__.py
frittomisto/asyncio.py
frittomisto/cfg.py
frittomisto/io.py
frittomisto/json.py
frittomisto/logging.py
frittomisto/path.py
frittomisto/profiling.py
frittomisto/time.py
frittomisto/url.py
frittomisto-0.0a2.dist-info/METADATA
frittomisto-0.0a2.dist-info/WHEEL
frittomisto-0.0a2.dist-info/RECORD
