Metadata-Version: 2.1
Name: frittomisto
Version: 0.0a2
Summary: A fried mix of python utilities
Author: werew
Requires-Python: >=3.8
Classifier: Programming Language :: Python :: 3
Classifier: Programming Language :: Python :: 3.8
Classifier: Programming Language :: Python :: 3.9
Classifier: Programming Language :: Python :: 3.10
Classifier: Programming Language :: Python :: 3.11
Classifier: Programming Language :: Python :: 3.12
Requires-Dist: toml (>=0.10.2,<0.11.0)
